{
    "$schema": "http://json-schema.org/draft-07/schema#",
    "$id": "https://schemas.artfully.london/v1/feed-venue.json",
    "type": "object",
    "definitions": {},
    "properties": {
        "entity": {
            "title": "Entity",
            "description": "Venue entity type",
            "const": "venue"
        },
        "venueId": {
            "title": "Venue ID",
            "description": "ID of the venue",
            "type": "string",
            "minLength": 1
        },
        "venueEntityId": {
            "title": "Venue Entity ID",
            "description": "Venue-unique ID of the entity",
            "type": "string",
            "minLength": 1
        },
        "rawContent": {
            "title": "Raw Content",
            "description": "The information to monitor for changes",
            "type": "string",
            "minLength": 1
        }
    },
    "required": [
        "entity",
        "venueId",
        "venueEntityId",
        "rawContent"
    ]
}